vikk_mcp/__init__.py
vikk_mcp/client.py
vikk_mcp/config.py
vikk_mcp/server.py
vikk_mcp/tools/__init__.py
vikk_legal_mcp-0.2.1.dist-info/METADATA
vikk_legal_mcp-0.2.1.dist-info/WHEEL
vikk_legal_mcp-0.2.1.dist-info/entry_points.txt
vikk_legal_mcp-0.2.1.dist-info/RECORD
