Metadata-Version: 2.4
Name: vikk-legal-mcp
Version: 0.2.1
Summary: MCP server for VIKK Legal AI Assistant - Generate legal documents via Claude Desktop
Project-URL: Homepage, https://vikk.ai
Project-URL: Documentation, https://lab.vikk.live/docs
Project-URL: Repository, https://github.com/vikkaird/vikkai-agentic-server
Author-email: VIKK AI <support@vikk.ai>
License-Expression: MIT
Keywords: ai,claude,documents,legal,mcp,pdf
Classifier: Development Status :: 4 - Beta
Classifier: Intended Audience :: Legal Industry
Classifier: License :: OSI Approved :: MIT License
Classifier: Programming Language :: Python :: 3
Classifier: Programming Language :: Python :: 3.10
Classifier: Programming Language :: Python :: 3.11
Classifier: Programming Language :: Python :: 3.12
Requires-Python: >=3.10
Requires-Dist: httpx>=0.27.0
Requires-Dist: mcp[cli]>=1.2.0
Requires-Dist: pydantic>=2.0.0
